vo_parquet/__init__.py
vo_parquet/metadata.py
vo_parquet/vo_parquet_table.py
voparquet-0.1.0.dist-info/licenses/LICENSE
voparquet-0.1.0.dist-info/METADATA
voparquet-0.1.0.dist-info/WHEEL
voparquet-0.1.0.dist-info/top_level.txt
voparquet-0.1.0.dist-info/RECORD
