Metadata-Version: 2.4
Name: VOparquet
Version: 0.1.0
Summary: Tools for VOParquet table data and metadata handling
Author-email: Trystan Lambert <trystanscottlambert@gmail.com>
License: MIT License
Requires-Python: >=3.8
License-File: LICENSE
Requires-Dist: pandas
Requires-Dist: numpy
Requires-Dist: astropy
Requires-Dist: pyarrow
Dynamic: license-file
